setup.py
ttv.py
ttv.egg-info/PKG-INFO
ttv.egg-info/SOURCES.txt
ttv.egg-info/dependency_links.txt
ttv.egg-info/requires.txt
ttv.egg-info/top_level.txt