Metadata-Version: 1.1
Name: ttv
Version: 0.0.1
Summary: A command line tool and a python library for test, train, validation set splitting
Home-page: https://github.com/coopie/ttv
Author: Sam Coope
Author-email: sam.j.coope@gmail.com
License: MIT
Download-URL: https://github.com/coopie/ttv/archive/master.zip
Platform: UNKNOWN
